aioaws/__init__.py
aioaws/_types.py
aioaws/_utils.py
aioaws/core.py
aioaws/py.typed
aioaws/s3.py
aioaws/ses.py
aioaws/sns.py
aioaws/sqs.py
aioaws/testing.py
aioaws/version.py
aioaws-0.15.1.dist-info/METADATA
aioaws-0.15.1.dist-info/WHEEL
aioaws-0.15.1.dist-info/licenses/LICENSE
aioaws-0.15.1.dist-info/RECORD
