Metadata-Version: 2.3
Name: aioaws
Version: 0.15.1
Summary: Asyncio SDK for some AWS services.
Project-URL: Homepage, https://github.com/samuelcolvin/aioaws
Project-URL: Funding, https://github.com/sponsors/samuelcolvin
Project-URL: Source, https://github.com/samuelcolvin/aioaws
Project-URL: Changelog, https://github.com/samuelcolvin/aioaws/releases
Author-email: Samuel Colvin <s@muelcolvin.com>
License-Expression: MIT
License-File: LICENSE
Classifier: Development Status :: 5 - Production/Stable
Classifier: Environment :: Console
Classifier: Environment :: MacOS X
Classifier: Intended Audience :: Developers
Classifier: Intended Audience :: Information Technology
Classifier: Intended Audience :: System Administrators
Classifier: License :: OSI Approved :: MIT License
Classifier: Operating System :: POSIX :: Linux
Classifier: Operating System :: Unix
Classifier: Programming Language :: Python
Classifier: Programming Language :: Python :: 3
Classifier: Programming Language :: Python :: 3 :: Only
Classifier: Programming Language :: Python :: 3.10
Classifier: Programming Language :: Python :: 3.11
Classifier: Programming Language :: Python :: 3.12
Classifier: Topic :: Internet
Classifier: Topic :: Software Development :: Libraries :: Python Modules
Requires-Python: >=3.10
Requires-Dist: aiofiles>=24
Requires-Dist: cryptography>=43
Requires-Dist: httpx>=0.27
Requires-Dist: pydantic-settings>=2.4.0
Requires-Dist: pydantic>=2.8
